profanex/__init__.py
profanex/filter.py
profanex/normalize.py
profanex/data/banned_words.yaml
profanex/data/excluded_words.yaml
profanex-0.0.2.dist-info/METADATA
profanex-0.0.2.dist-info/WHEEL
profanex-0.0.2.dist-info/licenses/LICENSE
profanex-0.0.2.dist-info/RECORD
