Metadata-Version: 2.4
Name: profanex
Version: 0.0.2
Author-email: jyablonski9 <jyablonski9@gmail.com>
Maintainer-email: jyablonski9 <jyablonski9@gmail.com>
License-Expression: MIT
License-File: LICENSE
Keywords: censorship,content-moderation,filtering,fuzzy-matching,normalization,profanity,text-processing
Classifier: Development Status :: 4 - Beta
Classifier: Intended Audience :: Developers
Classifier: License :: OSI Approved :: MIT License
Classifier: Programming Language :: Python :: 3
Classifier: Programming Language :: Python :: 3 :: Only
Classifier: Programming Language :: Python :: 3.10
Classifier: Programming Language :: Python :: 3.11
Classifier: Programming Language :: Python :: 3.12
Classifier: Programming Language :: Python :: 3.13
Classifier: Topic :: Text Processing :: Filters
Requires-Python: >=3.10
Requires-Dist: pyyaml>=6.0.2
Requires-Dist: rapidfuzz>=3.13.0
